pyftpkit/__about__.py
pyftpkit/__init__.py
pyftpkit/__main__.py
pyftpkit/_ftp.py
pyftpkit/_pathtrie.cpython-312-aarch64-linux-gnu.so
pyftpkit/_pathtrie.pyi
pyftpkit/_pool.py
pyftpkit/_pycurl.py
pyftpkit/connection_parameters.py
pyftpkit/exceptions.py
pyftpkit/ftpfs.py
pyftpkit/ftpfs.pyi
pyftpkit/loader.py
pyftpkit/loader.pyi
pyftpkit/logger_wrapper.py
pyftpkit/py.typed
pyftpkit/_pathtrie/.gitkeep
pyftpkit/_pathtrie/pathtrie.cpp
pyftpkit/_pathtrie/pathtrie.h
pyftpkit/_pathtrie/pathtrie_iterator.cpp
pyftpkit/_pathtrie/pathtrie_iterator.h
pyftpkit/_pathtrie/pathtrie_module.cpp
pyftpkit-0.1.2.dist-info/METADATA
pyftpkit-0.1.2.dist-info/WHEEL
pyftpkit-0.1.2.dist-info/entry_points.txt
pyftpkit-0.1.2.dist-info/RECORD
pyftpkit-0.1.2.dist-info/licenses/LICENSE
