Metadata-Version: 2.4
Name: pyftpkit
Version: 0.1.2
Summary: Asynchronous library for FTP-based file system operations
Author-Email: Vladislav Punko <iam.vlad.punko@gmail.com>
License-Expression: MIT
Classifier: Intended Audience :: Developers
Classifier: Intended Audience :: System Administrators
Classifier: Operating System :: MacOS :: MacOS X
Classifier: Operating System :: POSIX
Classifier: Topic :: Software Development :: Libraries :: Python Modules
Classifier: Topic :: Software Development :: Libraries
Classifier: Topic :: Software Development
Classifier: Topic :: Utilities
Classifier: Typing :: Typed
Classifier: Programming Language :: Python :: 3
Classifier: Programming Language :: Python :: 3.10
Classifier: Programming Language :: Python :: 3.11
Classifier: Programming Language :: Python :: 3.12
Classifier: Programming Language :: Python :: 3.13
Classifier: Programming Language :: Python :: 3.14
Project-URL: Issue tracker, https://github.com/vladpunko/pyftpkit/issues
Project-URL: Source code, https://github.com/vladpunko/pyftpkit
Requires-Python: >=3.10
Requires-Dist: pycurl<8,>=7.45.2
Requires-Dist: pydantic<3,>=2.7
Requires-Dist: pydantic_settings<3,>=2.10
